[
  {
    "fileName": "2.txt",
    "content": "<p><br></p>",
    "author": 2,
    "date": "2025-05-14T17:20:23.560Z"
  },
  {
    "fileName": "2.txt",
    "content": "<p>0</p>",
    "author": 2,
    "date": "2025-05-14T17:20:24.682Z"
  },
  {
    "fileName": "2.txt",
    "content": "<p>09</p>",
    "author": 2,
    "date": "2025-05-14T17:20:24.784Z"
  },
  {
    "fileName": "2.txt",
    "content": "<p>093</p>",
    "author": 2,
    "date": "2025-05-14T17:20:24.887Z"
  },
  {
    "fileName": "2.txt",
    "content": "<p>09312</p>",
    "author": 2,
    "date": "2025-05-14T17:20:25.002Z"
  },
  {
    "fileName": "2.txt",
    "content": "<p>0931238</p>",
    "author": 2,
    "date": "2025-05-14T17:20:25.243Z"
  },
  {
    "fileName": "2.txt",
    "content": "<p>09312384</p>",
    "author": 2,
    "date": "2025-05-14T17:20:25.466Z"
  },
  {
    "fileName": "2.txt",
    "content": "<p>093123840</p>",
    "author": 2,
    "date": "2025-05-14T17:20:25.794Z"
  },
  {
    "fileName": "2.txt",
    "content": "<p>0931238401</p>",
    "author": 2,
    "date": "2025-05-14T17:20:25.901Z"
  },
  {
    "fileName": "2.txt",
    "content": "<p>09312384012</p>",
    "author": 2,
    "date": "2025-05-14T17:20:26.004Z"
  },
  {
    "fileName": "2.txt",
    "content": "<p>093123840123</p>",
    "author": 2,
    "date": "2025-05-14T17:20:26.112Z"
  },
  {
    "fileName": "2.txt",
    "content": "<p>093123840123</p>",
    "author": 2,
    "date": "2025-05-14T17:20:28.752Z"
  },
  {
    "fileName": "2.txt",
    "content": "<p><br></p>",
    "author": 2,
    "date": "2025-05-14T17:22:54.599Z"
  },
  {
    "fileName": "2.txt",
    "content": "<p>PE</p>",
    "author": 2,
    "date": "2025-05-14T17:22:56.766Z"
  },
  {
    "fileName": "2.txt",
    "content": "<p>PEL</p>",
    "author": 2,
    "date": "2025-05-14T17:22:57.162Z"
  },
  {
    "fileName": "2.txt",
    "content": "<p>PELU</p>",
    "author": 2,
    "date": "2025-05-14T17:22:57.387Z"
  },
  {
    "fileName": "2.txt",
    "content": "<p>PELUQ</p>",
    "author": 2,
    "date": "2025-05-14T17:22:57.504Z"
  },
  {
    "fileName": "2.txt",
    "content": "<p>PELUQU</p>",
    "author": 2,
    "date": "2025-05-14T17:22:57.609Z"
  },
  {
    "fileName": "2.txt",
    "content": "<p>PELUQUER</p>",
    "author": 2,
    "date": "2025-05-14T17:22:58.131Z"
  },
  {
    "fileName": "2.txt",
    "content": "<p>PELUQUERI</p>",
    "author": 2,
    "date": "2025-05-14T17:22:58.233Z"
  },
  {
    "fileName": "2.txt",
    "content": "<p>PELUQUERIA</p>",
    "author": 2,
    "date": "2025-05-14T17:22:58.338Z"
  },
  {
    "fileName": "2.txt",
    "content": "<p>PELUQUERIA</p>",
    "author": 2,
    "date": "2025-05-14T17:23:00.506Z"
  },
  {
    "fileName": "2.txt",
    "content": "<p>PELUQUERIA</p>",
    "author": 2,
    "date": "2025-05-14T17:23:27.108Z"
  },
  {
    "fileName": "2.txt",
    "content": "<p><br></p>",
    "author": 2,
    "date": "2025-05-14T17:23:41.019Z"
  },
  {
    "fileName": "2.txt",
    "content": "<p>pe</p>",
    "author": 2,
    "date": "2025-05-14T17:23:46.181Z"
  },
  {
    "fileName": "2.txt",
    "content": "<p>ped</p>",
    "author": 2,
    "date": "2025-05-14T17:23:46.283Z"
  },
  {
    "fileName": "2.txt",
    "content": "<p>pedr</p>",
    "author": 2,
    "date": "2025-05-14T17:23:46.497Z"
  },
  {
    "fileName": "2.txt",
    "content": "<p>pedro</p>",
    "author": 2,
    "date": "2025-05-14T17:23:46.607Z"
  },
  {
    "fileName": "2.txt",
    "content": "<p>pedro&nbsp;</p>",
    "author": 2,
    "date": "2025-05-14T17:23:46.718Z"
  },
  {
    "fileName": "2.txt",
    "content": "<p>pedro s</p>",
    "author": 2,
    "date": "2025-05-14T17:23:46.832Z"
  },
  {
    "fileName": "2.txt",
    "content": "<p>pedro sn</p>",
    "author": 2,
    "date": "2025-05-14T17:23:47.040Z"
  },
  {
    "fileName": "2.txt",
    "content": "<p>pedro s</p>",
    "author": 2,
    "date": "2025-05-14T17:23:47.233Z"
  },
  {
    "fileName": "2.txt",
    "content": "<p>pedro sa</p>",
    "author": 2,
    "date": "2025-05-14T17:23:47.339Z"
  },
  {
    "fileName": "2.txt",
    "content": "<p>pedro san</p>",
    "author": 2,
    "date": "2025-05-14T17:23:47.441Z"
  },
  {
    "fileName": "2.txt",
    "content": "<p>pedro sanc</p>",
    "author": 2,
    "date": "2025-05-14T17:23:47.557Z"
  },
  {
    "fileName": "2.txt",
    "content": "<p>pedro sancsh</p>",
    "author": 2,
    "date": "2025-05-14T17:23:47.669Z"
  },
  {
    "fileName": "2.txt",
    "content": "<p>pedro sancshe</p>",
    "author": 2,
    "date": "2025-05-14T17:23:47.894Z"
  },
  {
    "fileName": "2.txt",
    "content": "<p>pedro sancsh</p>",
    "author": 2,
    "date": "2025-05-14T17:23:48.037Z"
  },
  {
    "fileName": "2.txt",
    "content": "<p>pedro sancs</p>",
    "author": 2,
    "date": "2025-05-14T17:23:48.200Z"
  },
  {
    "fileName": "2.txt",
    "content": "<p>pedro sanc</p>",
    "author": 2,
    "date": "2025-05-14T17:23:48.369Z"
  },
  {
    "fileName": "2.txt",
    "content": "<p>pedro sance</p>",
    "author": 2,
    "date": "2025-05-14T17:23:48.545Z"
  },
  {
    "fileName": "2.txt",
    "content": "<p>pedro sanc</p>",
    "author": 2,
    "date": "2025-05-14T17:23:48.802Z"
  },
  {
    "fileName": "2.txt",
    "content": "<p>pedro sanch</p>",
    "author": 2,
    "date": "2025-05-14T17:23:49.022Z"
  },
  {
    "fileName": "2.txt",
    "content": "<p>pedro sanche</p>",
    "author": 2,
    "date": "2025-05-14T17:23:49.134Z"
  },
  {
    "fileName": "2.txt",
    "content": "<p>pedro sanchez</p>",
    "author": 2,
    "date": "2025-05-14T17:23:49.356Z"
  },
  {
    "fileName": "2.txt",
    "content": "<p>pedro sanchez</p>",
    "author": 2,
    "date": "2025-05-14T17:23:51.000Z"
  },
  {
    "fileName": "2.txt",
    "content": "<p>pedro sanchez</p>",
    "author": 2,
    "date": "2025-05-14T17:25:13.812Z"
  },
  {
    "fileName": "2.txt",
    "content": "<p>pedro sanchez</p>",
    "author": 2,
    "date": "2025-05-14T17:26:01.543Z"
  },
  {
    "fileName": "2.txt",
    "content": "<p><br></p>",
    "author": 2,
    "date": "2025-05-14T17:26:09.425Z"
  },
  {
    "fileName": "2.txt",
    "content": "<p>ma</p>",
    "author": 2,
    "date": "2025-05-14T17:26:14.232Z"
  },
  {
    "fileName": "2.txt",
    "content": "<p>mar</p>",
    "author": 2,
    "date": "2025-05-14T17:26:14.337Z"
  },
  {
    "fileName": "2.txt",
    "content": "<p>mari</p>",
    "author": 2,
    "date": "2025-05-14T17:26:14.439Z"
  },
  {
    "fileName": "2.txt",
    "content": "<p>maria</p>",
    "author": 2,
    "date": "2025-05-14T17:26:14.653Z"
  },
  {
    "fileName": "2.txt",
    "content": "<p>marian</p>",
    "author": 2,
    "date": "2025-05-14T17:26:14.764Z"
  },
  {
    "fileName": "2.txt",
    "content": "<p>marianoi</p>",
    "author": 2,
    "date": "2025-05-14T17:26:14.870Z"
  },
  {
    "fileName": "2.txt",
    "content": "<p>marianoi&nbsp;</p>",
    "author": 2,
    "date": "2025-05-14T17:26:15.203Z"
  },
  {
    "fileName": "2.txt",
    "content": "<p>marianoi ra</p>",
    "author": 2,
    "date": "2025-05-14T17:26:15.591Z"
  },
  {
    "fileName": "2.txt",
    "content": "<p>marianoi ray</p>",
    "author": 2,
    "date": "2025-05-14T17:26:15.710Z"
  },
  {
    "fileName": "2.txt",
    "content": "<p>marianoi rayo</p>",
    "author": 2,
    "date": "2025-05-14T17:26:16.325Z"
  },
  {
    "fileName": "2.txt",
    "content": "<p>marianoi rayou</p>",
    "author": 2,
    "date": "2025-05-14T17:26:16.595Z"
  },
  {
    "fileName": "2.txt",
    "content": "<p>marianoi rayo</p>",
    "author": 2,
    "date": "2025-05-14T17:26:16.879Z"
  },
  {
    "fileName": "2.txt",
    "content": "<p>marianoi rayoy</p>",
    "author": 2,
    "date": "2025-05-14T17:26:17.303Z"
  },
  {
    "fileName": "2.txt",
    "content": "<p>marianoi rayoy</p>",
    "author": 2,
    "date": "2025-05-14T17:26:20.124Z"
  },
  {
    "fileName": "2.txt",
    "content": "<p>pedro sanchez</p>",
    "author": 2,
    "date": "2025-05-14T17:26:23.166Z"
  },
  {
    "fileName": "2.txt",
    "content": "<p>marianoi rayoy</p>",
    "author": 2,
    "date": "2025-05-14T17:26:23.526Z"
  },
  {
    "fileName": "2.txt",
    "content": "<p>pedro sanchez</p>",
    "author": 2,
    "date": "2025-05-14T17:26:24.067Z"
  },
  {
    "fileName": "2.txt",
    "content": "<p>marianoi rayoy</p>",
    "author": 2,
    "date": "2025-05-14T17:26:24.390Z"
  },
  {
    "fileName": "2.txt",
    "content": "<p>pedro sanchez</p>",
    "author": 2,
    "date": "2025-05-14T17:26:26.455Z"
  },
  {
    "fileName": "2.txt",
    "content": "<p>marianoi rayoy</p>",
    "author": 2,
    "date": "2025-05-14T17:26:34.091Z"
  },
  {
    "fileName": "2.txt",
    "content": "<p>marianoi rayoy</p>",
    "author": 2,
    "date": "2025-05-14T17:26:41.882Z"
  },
  {
    "fileName": "2.txt",
    "content": "<p>PELUQUERIA</p>",
    "author": 2,
    "date": "2025-05-14T17:26:44.389Z"
  },
  {
    "fileName": "2.txt",
    "content": "<p>marianoi rayoy</p>",
    "author": 2,
    "date": "2025-05-14T17:26:47.093Z"
  },
  {
    "fileName": "2.txt",
    "content": "<p>marianoi rayoy</p>",
    "author": 2,
    "date": "2025-05-14T17:26:48.984Z"
  },
  {
    "fileName": "2.txt",
    "content": "<p>PELUQUERIA</p>",
    "author": 2,
    "date": "2025-05-14T17:26:52.199Z"
  },
  {
    "fileName": "2.txt",
    "content": "<p>PELUQUERIA</p>",
    "author": 2,
    "date": "2025-05-14T17:26:57.245Z"
  },
  {
    "fileName": "2.txt",
    "content": "<p><br></p><p>pedro sanchez</p>",
    "author": 2,
    "date": "2025-05-14T17:27:01.334Z"
  },
  {
    "fileName": "2.txt",
    "content": "<p>PELUQUERIA</p>",
    "author": 2,
    "date": "2025-05-14T17:27:01.731Z"
  },
  {
    "fileName": "2.txt",
    "content": "<p><br></p><p>pedro sanchez</p>",
    "author": 2,
    "date": "2025-05-14T17:27:02.158Z"
  },
  {
    "fileName": "2.txt",
    "content": "<p>marianoi rayoy</p>",
    "author": 2,
    "date": "2025-05-14T17:27:03.401Z"
  },
  {
    "fileName": "2.txt",
    "content": "<p>marianoi rayoy</p>",
    "author": 2,
    "date": "2025-05-14T17:30:08.955Z"
  },
  {
    "fileName": "2.txt",
    "content": "<p><br></p><p>pedro sanchez</p>",
    "author": 2,
    "date": "2025-05-14T17:30:10.181Z"
  },
  {
    "fileName": "2.txt",
    "content": "<p>marianoi rayoy</p>",
    "author": 2,
    "date": "2025-05-14T17:30:14.683Z"
  },
  {
    "fileName": "2.txt",
    "content": "<p><br></p><p>pedro sanchez&nbsp;</p>",
    "author": 2,
    "date": "2025-05-14T17:30:15.631Z"
  },
  {
    "fileName": "2.txt",
    "content": "<p><br></p><p>pedro sanchez pa</p>",
    "author": 2,
    "date": "2025-05-14T17:30:16.134Z"
  },
  {
    "fileName": "2.txt",
    "content": "<p><br></p><p>pedro sanchez pat</p>",
    "author": 2,
    "date": "2025-05-14T17:30:16.630Z"
  },
  {
    "fileName": "2.txt",
    "content": "<p><br></p><p>pedro sanchez pata</p>",
    "author": 2,
    "date": "2025-05-14T17:30:16.839Z"
  },
  {
    "fileName": "2.txt",
    "content": "<p><br></p><p>pedro sanchez patat</p>",
    "author": 2,
    "date": "2025-05-14T17:30:16.947Z"
  },
  {
    "fileName": "2.txt",
    "content": "<p><br></p><p>pedro sanchez patata</p>",
    "author": 2,
    "date": "2025-05-14T17:30:17.061Z"
  },
  {
    "fileName": "2.txt",
    "content": "<p><br></p><p>pedro sanchez patata</p>",
    "author": 2,
    "date": "2025-05-14T17:30:17.967Z"
  },
  {
    "fileName": "2.txt",
    "content": "<p>marianoi rayoy</p>",
    "author": 2,
    "date": "2025-05-14T17:30:26.041Z"
  },
  {
    "fileName": "2.txt",
    "content": "<p><br></p><p>pedro sanchez patata</p>",
    "author": 2,
    "date": "2025-05-14T17:30:58.631Z"
  },
  {
    "fileName": "2.txt",
    "content": "<p><br></p><p>pedro sanchez patata</p>",
    "author": 2,
    "date": "2025-05-14T17:38:39.905Z"
  },
  {
    "fileName": "2.txt",
    "content": "<p><br></p><p>pedro sanchez patata</p>",
    "author": 2,
    "date": "2025-05-14T17:38:44.000Z"
  },
  {
    "fileName": "2.txt",
    "content": "<p><br></p>",
    "author": 2,
    "date": "2025-05-14T17:50:24.631Z"
  },
  {
    "fileName": "2.txt",
    "content": "<p><br></p>",
    "author": 2,
    "date": "2025-05-14T17:51:03.251Z"
  },
  {
    "fileName": "2.txt",
    "content": "<p><br></p>",
    "author": 2,
    "date": "2025-05-14T17:52:24.961Z"
  },
  {
    "fileName": "2.txt",
    "content": "<p>s</p>",
    "author": 2,
    "date": "2025-05-14T17:52:25.456Z"
  },
  {
    "fileName": "2.txt",
    "content": "<p>sd</p>",
    "author": 2,
    "date": "2025-05-14T17:52:25.560Z"
  },
  {
    "fileName": "2.txt",
    "content": "<p>sdas</p>",
    "author": 2,
    "date": "2025-05-14T17:52:25.665Z"
  },
  {
    "fileName": "2.txt",
    "content": "<p>sdasd</p>",
    "author": 2,
    "date": "2025-05-14T17:52:25.775Z"
  },
  {
    "fileName": "2.txt",
    "content": "<p>sdasdas</p>",
    "author": 2,
    "date": "2025-05-14T17:52:25.882Z"
  },
  {
    "fileName": "2.txt",
    "content": "<p>sdasdasd</p>",
    "author": 2,
    "date": "2025-05-14T17:52:25.991Z"
  },
  {
    "fileName": "2.txt",
    "content": "<p>sdasdasd</p>",
    "author": 2,
    "date": "2025-05-14T17:52:26.514Z"
  },
  {
    "fileName": "2.txt",
    "content": "<p>sdasdasd</p>",
    "author": 2,
    "date": "2025-05-14T17:53:04.104Z"
  },
  {
    "fileName": "2.txt",
    "content": "<p>sdasdasd</p>",
    "author": 2,
    "date": "2025-05-15T16:03:08.793Z"
  },
  {
    "fileName": "2.txt",
    "content": "<p>sdasdasd</p>",
    "author": 2,
    "date": "2025-05-15T16:03:14.944Z"
  },
  {
    "fileName": "2.txt",
    "content": "<p>sdasdasd</p>",
    "author": 2,
    "date": "2025-05-15T16:03:18.785Z"
  },
  {
    "fileName": "2.txt",
    "content": "<p>sdasdasd</p>",
    "author": 2,
    "date": "2025-05-15T16:03:20.389Z"
  },
  {
    "fileName": "2.txt",
    "content": "<p>sdasdasd</p>",
    "author": 2,
    "date": "2025-05-15T16:03:22.138Z"
  },
  {
    "fileName": "2.txt",
    "content": "<p></p><p>sdasdasd</p>",
    "author": 2,
    "date": "2025-05-15T16:03:58.631Z"
  },
  {
    "fileName": "2.txt",
    "content": "<p><br></p><p>sdasdasd</p>",
    "author": 2,
    "date": "2025-05-15T16:04:01.250Z"
  },
  {
    "fileName": "2.txt",
    "content": "<p><br></p><p>sdasdasd</p>",
    "author": 2,
    "date": "2025-05-15T16:04:02.413Z"
  },
  {
    "fileName": "2.txt",
    "content": "<p><br></p><p>sdasdasd</p>",
    "author": 2,
    "date": "2025-05-15T16:04:25.122Z"
  },
  {
    "fileName": "2.txt",
    "content": "<p><br></p><p>sdasdasd</p>",
    "author": 2,
    "date": "2025-05-15T16:04:27.695Z"
  },
  {
    "fileName": "2.txt",
    "content": "<p><br></p><p>sdasdasd</p>",
    "author": 2,
    "date": "2025-05-15T16:04:32.525Z"
  },
  {
    "fileName": "2.txt",
    "content": "<p><br></p><p>sdasdasd</p>",
    "author": 2,
    "date": "2025-05-15T16:04:38.698Z"
  },
  {
    "fileName": "2.txt",
    "content": "<p><br></p><p>sdasdasd</p>",
    "author": 2,
    "date": "2025-05-15T16:04:40.558Z"
  },
  {
    "fileName": "2.txt",
    "content": "<p><br></p><p>sdasdasd</p>",
    "author": 2,
    "date": "2025-05-15T16:04:41.825Z"
  },
  {
    "fileName": "2.txt",
    "content": "<p><br></p><p>sdasdasd</p>",
    "author": 2,
    "date": "2025-05-15T16:04:43.678Z"
  },
  {
    "fileName": "2.txt",
    "content": "<p><br></p><p>sdasdasd</p>",
    "author": 2,
    "date": "2025-05-15T16:04:44.720Z"
  },
  {
    "fileName": "2.txt",
    "content": "<p><br></p><p>sdasdasd</p>",
    "author": 2,
    "date": "2025-05-15T16:04:45.748Z"
  },
  {
    "fileName": "2.txt",
    "content": "<p><br></p><p>sdasdasd</p>",
    "author": 2,
    "date": "2025-05-15T16:04:46.895Z"
  },
  {
    "fileName": "2.txt",
    "content": "<p><br></p><p>sdasdasd</p>",
    "author": 2,
    "date": "2025-05-15T16:04:57.680Z"
  },
  {
    "fileName": "2.txt",
    "content": "<p><br></p><p>sd</p>",
    "author": 2,
    "date": "2025-05-15T16:05:01.309Z"
  },
  {
    "fileName": "2.txt",
    "content": "<p><br></p><p>sdf</p>",
    "author": 2,
    "date": "2025-05-15T16:05:01.413Z"
  },
  {
    "fileName": "2.txt",
    "content": "<p><br></p><p>sdfg</p>",
    "author": 2,
    "date": "2025-05-15T16:05:01.625Z"
  },
  {
    "fileName": "2.txt",
    "content": "<p><br></p><p>sdfgs</p>",
    "author": 2,
    "date": "2025-05-15T16:05:01.726Z"
  },
  {
    "fileName": "2.txt",
    "content": "<p><br></p><p>sdfgsdf</p>",
    "author": 2,
    "date": "2025-05-15T16:05:01.827Z"
  },
  {
    "fileName": "2.txt",
    "content": "<p><br></p><p>sdfgsdfg&nbsp;</p>",
    "author": 2,
    "date": "2025-05-15T16:05:02.062Z"
  },
  {
    "fileName": "2.txt",
    "content": "<p><br></p><p>sdfgsdfg s</p>",
    "author": 2,
    "date": "2025-05-15T16:05:02.264Z"
  },
  {
    "fileName": "2.txt",
    "content": "<p><br></p><p>sdfgsdfg sd</p>",
    "author": 2,
    "date": "2025-05-15T16:05:02.366Z"
  },
  {
    "fileName": "2.txt",
    "content": "<p><br></p><p>sdfgsdfg sdf</p>",
    "author": 2,
    "date": "2025-05-15T16:05:02.467Z"
  },
  {
    "fileName": "2.txt",
    "content": "<p><br></p><p>sdfgsdfg sdfg</p>",
    "author": 2,
    "date": "2025-05-15T16:05:02.568Z"
  },
  {
    "fileName": "2.txt",
    "content": "<p><br></p><p>sdfgsdfg sdfg&nbsp;</p>",
    "author": 2,
    "date": "2025-05-15T16:05:02.771Z"
  },
  {
    "fileName": "2.txt",
    "content": "<p><br></p><p>sdfgsdfg sdfg sd</p>",
    "author": 2,
    "date": "2025-05-15T16:05:02.973Z"
  },
  {
    "fileName": "2.txt",
    "content": "<p><br></p><p>sdfgsdfg sdfg sdf</p>",
    "author": 2,
    "date": "2025-05-15T16:05:03.074Z"
  },
  {
    "fileName": "2.txt",
    "content": "<p><br></p><p>sdfgsdfg sdfg sdfg</p>",
    "author": 2,
    "date": "2025-05-15T16:05:03.327Z"
  },
  {
    "fileName": "2.txt",
    "content": "<p><br></p><p>sdfgsdfg sdfg sdfg&nbsp;</p>",
    "author": 2,
    "date": "2025-05-15T16:05:03.428Z"
  },
  {
    "fileName": "2.txt",
    "content": "<p><br></p><p>sdfgsdfg sdfg sdfg s</p>",
    "author": 2,
    "date": "2025-05-15T16:05:03.630Z"
  },
  {
    "fileName": "2.txt",
    "content": "<p><br></p><p>sdfgsdfg sdfg sdfg sd</p>",
    "author": 2,
    "date": "2025-05-15T16:05:03.732Z"
  },
  {
    "fileName": "2.txt",
    "content": "<p><br></p><p>sdfgsdfg sdfg sdfg sdf</p>",
    "author": 2,
    "date": "2025-05-15T16:05:03.841Z"
  },
  {
    "fileName": "2.txt",
    "content": "<p><br></p><p>sdfgsdfg sdfg sdfg sdfg</p>",
    "author": 2,
    "date": "2025-05-15T16:05:04.143Z"
  },
  {
    "fileName": "2.txt",
    "content": "<p><br></p><p>sdfgsdfg sdfg sdfg sdfg&nbsp;</p>",
    "author": 2,
    "date": "2025-05-15T16:05:04.363Z"
  },
  {
    "fileName": "2.txt",
    "content": "<p><br></p><p>sdfgsdfg sdfg sdfg sdfg s</p>",
    "author": 2,
    "date": "2025-05-15T16:05:04.684Z"
  },
  {
    "fileName": "2.txt",
    "content": "<p><br></p><p>sdfgsdfg sdfg sdfg sdfg sd</p>",
    "author": 2,
    "date": "2025-05-15T16:05:04.786Z"
  },
  {
    "fileName": "2.txt",
    "content": "<p><br></p><p>sdfgsdfg sdfg sdfg sdfg sdf</p>",
    "author": 2,
    "date": "2025-05-15T16:05:04.893Z"
  },
  {
    "fileName": "2.txt",
    "content": "<p><br></p><p>sdfgsdfg sdfg sdfg sdfg sdfg</p>",
    "author": 2,
    "date": "2025-05-15T16:05:05.107Z"
  },
  {
    "fileName": "2.txt",
    "content": "<p><br></p><p>sdfgsdfg sdfg sdfg sdfg sdfg&nbsp;</p>",
    "author": 2,
    "date": "2025-05-15T16:05:05.310Z"
  },
  {
    "fileName": "2.txt",
    "content": "<p><br></p><p>sdfgsdfg sdfg sdfg sdfg sdfg s</p>",
    "author": 2,
    "date": "2025-05-15T16:05:05.634Z"
  },
  {
    "fileName": "2.txt",
    "content": "<p><br></p><p>sdfgsdfg sdfg sdfg sdfg sdfg sd</p>",
    "author": 2,
    "date": "2025-05-15T16:05:05.735Z"
  },
  {
    "fileName": "2.txt",
    "content": "<p><br></p><p>sdfgsdfg sdfg sdfg sdfg sdfg sdfg</p>",
    "author": 2,
    "date": "2025-05-15T16:05:05.836Z"
  },
  {
    "fileName": "2.txt",
    "content": "<p><br></p><p>sdfgsdfg sdfg sdfg sdfg sdfg sdfg&nbsp;</p>",
    "author": 2,
    "date": "2025-05-15T16:05:06.038Z"
  },
  {
    "fileName": "2.txt",
    "content": "<p><br></p><p>sdfgsdfg sdfg sdfg sdfg sdfg sdfg&nbsp; &nbsp;&nbsp;</p>",
    "author": 2,
    "date": "2025-05-15T16:05:06.682Z"
  },
  {
    "fileName": "2.txt",
    "content": "<p><br></p><p>sdfgsdfg sdfg sdfg sdfg sdfg sdfg&nbsp; &nbsp; &nbsp;</p>",
    "author": 2,
    "date": "2025-05-15T16:05:06.784Z"
  },
  {
    "fileName": "2.txt",
    "content": "<p><br></p><p>sdfgsdfg sdfg sdfg sdfg sdfg sdfg&nbsp; &nbsp; &nbsp;&nbsp;</p>",
    "author": 2,
    "date": "2025-05-15T16:05:06.885Z"
  },
  {
    "fileName": "2.txt",
    "content": "<p><br></p><p>sdfgsdfg sdfg sdfg sdfg sdfg sdfg&nbsp; &nbsp; &nbsp; &nbsp;</p>",
    "author": 2,
    "date": "2025-05-15T16:05:07.087Z"
  },
  {
    "fileName": "2.txt",
    "content": "<p><br></p><p>sdfgsdfg sdfg sdfg sdfg sdfg sdfg&nbsp; &nbsp; &nbsp; &nbsp;a</p>",
    "author": 2,
    "date": "2025-05-15T16:05:07.404Z"
  },
  {
    "fileName": "2.txt",
    "content": "<p><br></p><p>sdfgsdfg sdfg sdfg sdfg sdfg sdfg&nbsp; &nbsp; &nbsp; &nbsp;asd</p>",
    "author": 2,
    "date": "2025-05-15T16:05:07.635Z"
  },
  {
    "fileName": "2.txt",
    "content": "<p><br></p><p>sdfgsdfg sdfg sdfg sdfg sdfg sdfg&nbsp; &nbsp; &nbsp; &nbsp;asdf</p>",
    "author": 2,
    "date": "2025-05-15T16:05:07.737Z"
  },
  {
    "fileName": "2.txt",
    "content": "<p><br></p><p>sdfgsdfg sdfg sdfg sdfg sdfg sdfg&nbsp; &nbsp; &nbsp; &nbsp;asdf&nbsp;</p>",
    "author": 2,
    "date": "2025-05-15T16:05:08.088Z"
  },
  {
    "fileName": "2.txt",
    "content": "<p><br></p><p>sdfgsdfg sdfg sdfg sdfg sdfg sdfg&nbsp; &nbsp; &nbsp; &nbsp;asdf a</p>",
    "author": 2,
    "date": "2025-05-15T16:05:08.189Z"
  },
  {
    "fileName": "2.txt",
    "content": "<p><br></p><p>sdfgsdfg sdfg sdfg sdfg sdfg sdfg&nbsp; &nbsp; &nbsp; &nbsp;asdf asd</p>",
    "author": 2,
    "date": "2025-05-15T16:05:08.290Z"
  },
  {
    "fileName": "2.txt",
    "content": "<p><br></p><p>sdfgsdfg sdfg sdfg sdfg sdfg sdfg&nbsp; &nbsp; &nbsp; &nbsp;asdf asdf</p>",
    "author": 2,
    "date": "2025-05-15T16:05:08.391Z"
  },
  {
    "fileName": "2.txt",
    "content": "<p><br></p><p>sdfgsdfg sdfg sdfg sdfg sdfg sdfg&nbsp; &nbsp; &nbsp; &nbsp;asdf asdf&nbsp;</p>",
    "author": 2,
    "date": "2025-05-15T16:05:08.594Z"
  },
  {
    "fileName": "2.txt",
    "content": "<p><br></p><p>sdfgsdfg sdfg sdfg sdfg sdfg sdfg&nbsp; &nbsp; &nbsp; &nbsp;asdf asdf&nbsp;</p>",
    "author": 2,
    "date": "2025-05-15T16:05:09.695Z"
  },
  {
    "fileName": "2.txt",
    "content": "<p><br></p><p>sdfgsdfg sdfg sdfg sdfg sdfg sdfg&nbsp; &nbsp; &nbsp; &nbsp;asdf asdf&nbsp;</p>",
    "author": 2,
    "date": "2025-05-15T16:05:11.068Z"
  },
  {
    "fileName": "2.txt",
    "content": "<p><br></p><p>sdfgsdfg sdfg sdfg sdfg sdfg sdfg&nbsp; &nbsp; &nbsp; &nbsp;asdf asdf&nbsp;</p><p></p>",
    "author": 2,
    "date": "2025-05-15T16:05:11.647Z"
  },
  {
    "fileName": "2.txt",
    "content": "<p><br></p><p>sdfgsdfg sdfg sdfg sdfg sdfg sdfg&nbsp; &nbsp; &nbsp; &nbsp;asdf asdf&nbsp;</p><p><br></p>",
    "author": 2,
    "date": "2025-05-15T16:05:12.479Z"
  },
  {
    "fileName": "2.txt",
    "content": "<p><br></p><p>sdfgsdfg sdfg sdfg sdfg sdfg sdfg&nbsp; &nbsp; &nbsp; &nbsp;asdf asdf&nbsp;</p><p><br></p>",
    "author": 2,
    "date": "2025-05-15T16:05:13.258Z"
  },
  {
    "fileName": "2.txt",
    "content": "<p><br></p><p>sdfgsdfg sdfg sdfg sdfg sdfg sdfg&nbsp; &nbsp; &nbsp; &nbsp;asdf asdf&nbsp;</p><p><br></p>",
    "author": 2,
    "date": "2025-05-15T16:05:13.860Z"
  },
  {
    "fileName": "2.txt",
    "content": "<p><br></p><p>sdfgsdfg sdfg sdfg sdfg sdfg sdfg&nbsp; &nbsp; &nbsp; &nbsp;asdf asdf&nbsp;&nbsp;</p><p><br></p>",
    "author": 2,
    "date": "2025-05-15T16:06:34.627Z"
  },
  {
    "fileName": "2.txt",
    "content": "<p><br></p><p>sdfgsdfg sdfg sdfg sdfg sdfg sdfg&nbsp; &nbsp; &nbsp; &nbsp;asdf asdf&nbsp; a</p><p><br></p>",
    "author": 2,
    "date": "2025-05-15T16:06:34.729Z"
  },
  {
    "fileName": "2.txt",
    "content": "<p><br></p><p>sdfgsdfg sdfg sdfg sdfg sdfg sdfg&nbsp; &nbsp; &nbsp; &nbsp;asdf asdf&nbsp; as</p><p><br></p>",
    "author": 2,
    "date": "2025-05-15T16:06:34.830Z"
  },
  {
    "fileName": "2.txt",
    "content": "<p><br></p><p>sdfgsdfg sdfg sdfg sdfg sdfg sdfg&nbsp; &nbsp; &nbsp; &nbsp;asdf asdf&nbsp; asd</p><p><br></p>",
    "author": 2,
    "date": "2025-05-15T16:06:35.032Z"
  },
  {
    "fileName": "2.txt",
    "content": "<p><br></p><p>sdfgsdfg sdfg sdfg sdfg sdfg sdfg&nbsp; &nbsp; &nbsp; &nbsp;asdf asdf&nbsp; asda</p><p><br></p>",
    "author": 2,
    "date": "2025-05-15T16:06:35.133Z"
  },
  {
    "fileName": "2.txt",
    "content": "<p><br></p><p>sdfgsdfg sdfg sdfg sdfg sdfg sdfg&nbsp; &nbsp; &nbsp; &nbsp;asdf asdf&nbsp; asdas</p><p><br></p>",
    "author": 2,
    "date": "2025-05-15T16:06:35.234Z"
  },
  {
    "fileName": "2.txt",
    "content": "<p><br></p><p>sdfgsdfg sdfg sdfg sdfg sdfg sdfg&nbsp; &nbsp; &nbsp; &nbsp;asdf asdf&nbsp; asdasd</p><p><br></p>",
    "author": 2,
    "date": "2025-05-15T16:06:35.441Z"
  },
  {
    "fileName": "2.txt",
    "content": "<p><br></p><p>sdfgsdfg sdfg sdfg sdfg sdfg sdfg&nbsp; &nbsp; &nbsp; &nbsp;asdf asdf&nbsp; asdasd&nbsp;</p><p><br></p>",
    "author": 2,
    "date": "2025-05-15T16:06:35.542Z"
  },
  {
    "fileName": "2.txt",
    "content": "<p><br></p><p>sdfgsdfg sdfg sdfg sdfg sdfg sdfg&nbsp; &nbsp; &nbsp; &nbsp;asdf asdf&nbsp; asdasd a</p><p><br></p>",
    "author": 2,
    "date": "2025-05-15T16:06:35.643Z"
  },
  {
    "fileName": "2.txt",
    "content": "<p><br></p><p>sdfgsdfg sdfg sdfg sdfg sdfg sdfg&nbsp; &nbsp; &nbsp; &nbsp;asdf asdf&nbsp; asdasd as</p><p><br></p>",
    "author": 2,
    "date": "2025-05-15T16:06:35.744Z"
  },
  {
    "fileName": "2.txt",
    "content": "<p><br></p><p>sdfgsdfg sdfg sdfg sdfg sdfg sdfg&nbsp; &nbsp; &nbsp; &nbsp;asdf asdf&nbsp; asdasd asd</p><p><br></p>",
    "author": 2,
    "date": "2025-05-15T16:06:35.844Z"
  },
  {
    "fileName": "2.txt",
    "content": "<p><br></p><p>sdfgsdfg sdfg sdfg sdfg sdfg sdfg&nbsp; &nbsp; &nbsp; &nbsp;asdf asdf&nbsp; asdasd asd</p><p><br></p>",
    "author": 2,
    "date": "2025-05-15T16:06:36.022Z"
  },
  {
    "fileName": "2.txt",
    "content": "<p><br></p><p>sdfgsdfg sdfg sdfg sdfg sdfg sdfg&nbsp; &nbsp; &nbsp; &nbsp;asdf asdf&nbsp;</p><p>a</p>",
    "author": 2,
    "date": "2025-05-15T16:06:38.063Z"
  },
  {
    "fileName": "2.txt",
    "content": "<p><br></p><p>sdfgsdfg sdfg sdfg sdfg sdfg sdfg&nbsp; &nbsp; &nbsp; &nbsp;asdf asdf&nbsp;</p><p>as</p>",
    "author": 2,
    "date": "2025-05-15T16:06:38.165Z"
  },
  {
    "fileName": "2.txt",
    "content": "<p><br></p><p>sdfgsdfg sdfg sdfg sdfg sdfg sdfg&nbsp; &nbsp; &nbsp; &nbsp;asdf asdf&nbsp;</p><p>asd</p>",
    "author": 2,
    "date": "2025-05-15T16:06:38.267Z"
  },
  {
    "fileName": "2.txt",
    "content": "<p><br></p><p>sdfgsdfg sdfg sdfg sdfg sdfg sdfg&nbsp; &nbsp; &nbsp; &nbsp;asdf asdf&nbsp;</p><p>asda</p>",
    "author": 2,
    "date": "2025-05-15T16:06:38.368Z"
  },
  {
    "fileName": "2.txt",
    "content": "<p><br></p><p>sdfgsdfg sdfg sdfg sdfg sdfg sdfg&nbsp; &nbsp; &nbsp; &nbsp;asdf asdf&nbsp;</p><p>asdas</p>",
    "author": 2,
    "date": "2025-05-15T16:06:38.470Z"
  },
  {
    "fileName": "2.txt",
    "content": "<p><br></p><p>sdfgsdfg sdfg sdfg sdfg sdfg sdfg&nbsp; &nbsp; &nbsp; &nbsp;asdf asdf&nbsp;</p><p>asdasd</p>",
    "author": 2,
    "date": "2025-05-15T16:06:38.572Z"
  },
  {
    "fileName": "2.txt",
    "content": "<p><br></p><p>sdfgsdfg sdfg sdfg sdfg sdfg sdfg&nbsp; &nbsp; &nbsp; &nbsp;asdf asdf&nbsp;</p><p>asdasdas</p>",
    "author": 2,
    "date": "2025-05-15T16:06:38.781Z"
  },
  {
    "fileName": "2.txt",
    "content": "<p><br></p><p>sdfgsdfg sdfg sdfg sdfg sdfg sdfg&nbsp; &nbsp; &nbsp; &nbsp;asdf asdf&nbsp;</p><p>asdasdasd</p>",
    "author": 2,
    "date": "2025-05-15T16:06:38.883Z"
  },
  {
    "fileName": "2.txt",
    "content": "<p><br></p><p>sdfgsdfg sdfg sdfg sdfg sdfg sdfg&nbsp; &nbsp; &nbsp; &nbsp;asdf asdf&nbsp;</p><p>asdasdasd&nbsp;</p>",
    "author": 2,
    "date": "2025-05-15T16:06:38.984Z"
  },
  {
    "fileName": "2.txt",
    "content": "<p><br></p><p>sdfgsdfg sdfg sdfg sdfg sdfg sdfg&nbsp; &nbsp; &nbsp; &nbsp;asdf asdf&nbsp;</p><p>asdasdasd a</p>",
    "author": 2,
    "date": "2025-05-15T16:06:39.086Z"
  },
  {
    "fileName": "2.txt",
    "content": "<p><br></p><p>sdfgsdfg sdfg sdfg sdfg sdfg sdfg&nbsp; &nbsp; &nbsp; &nbsp;asdf asdf&nbsp;</p><p>asdasdasd a</p>",
    "author": 2,
    "date": "2025-05-15T16:06:39.498Z"
  },
  {
    "fileName": "2.txt",
    "content": "<p><br></p><p>sdfgsdfg sdfg sdfg sdfg sdfg sdfg&nbsp; &nbsp; &nbsp; &nbsp;asdf asdf&nbsp;</p><p>asdasdasd a&nbsp;</p>",
    "author": 2,
    "date": "2025-05-15T16:06:41.036Z"
  },
  {
    "fileName": "2.txt",
    "content": "<p><br></p><p>sdfgsdfg sdfg sdfg sdfg sdfg sdfg&nbsp; &nbsp; &nbsp; &nbsp;asdf asdf&nbsp;</p><p>asdasdasd a a</p>",
    "author": 2,
    "date": "2025-05-15T16:06:41.138Z"
  },
  {
    "fileName": "2.txt",
    "content": "<p><br></p><p>sdfgsdfg sdfg sdfg sdfg sdfg sdfg&nbsp; &nbsp; &nbsp; &nbsp;asdf asdf&nbsp;</p><p>asdasdasd a asd</p>",
    "author": 2,
    "date": "2025-05-15T16:06:41.344Z"
  },
  {
    "fileName": "2.txt",
    "content": "<p><br></p><p>sdfgsdfg sdfg sdfg sdfg sdfg sdfg&nbsp; &nbsp; &nbsp; &nbsp;asdf asdf&nbsp;</p><p>asdasdasd a asdas</p>",
    "author": 2,
    "date": "2025-05-15T16:06:41.546Z"
  },
  {
    "fileName": "2.txt",
    "content": "<p><br></p><p>sdfgsdfg sdfg sdfg sdfg sdfg sdfg&nbsp; &nbsp; &nbsp; &nbsp;asdf asdf&nbsp;</p><p>asdasdasd a asdasd</p>",
    "author": 2,
    "date": "2025-05-15T16:06:41.649Z"
  },
  {
    "fileName": "2.txt",
    "content": "<p><br></p><p>sdfgsdfg sdfg sdfg sdfg sdfg sdfg&nbsp; &nbsp; &nbsp; &nbsp;asdf asdf&nbsp;</p><p>asdasdasd a asdasd&nbsp;</p>",
    "author": 2,
    "date": "2025-05-15T16:06:41.751Z"
  },
  {
    "fileName": "2.txt",
    "content": "<p><br></p><p>sdfgsdfg sdfg sdfg sdfg sdfg sdfg&nbsp; &nbsp; &nbsp; &nbsp;asdf asdf&nbsp;</p><p>asdasdasd a asdasd&nbsp;</p>",
    "author": 2,
    "date": "2025-05-15T16:06:42.144Z"
  },
  {
    "fileName": "2.txt",
    "content": "<p><br></p><p>sdfgsdfg sdfg sdfg sdfg sdfg sdfg&nbsp; &nbsp; &nbsp; &nbsp;asdf asdf&nbsp;</p><p>asdasdasd a asdasd&nbsp;</p>",
    "author": 2,
    "date": "2025-05-15T16:06:50.390Z"
  },
  {
    "fileName": "2.txt",
    "content": "<p><br></p><p>sdfgsdfg sdfg sdfg sdfg sdfg sdfg&nbsp; &nbsp; &nbsp; &nbsp;asdf asdf&nbsp;</p><p>asdasdasd a asdasd&nbsp;</p>",
    "author": 2,
    "date": "2025-05-15T16:06:52.009Z"
  },
  {
    "fileName": "2.txt",
    "content": "<p><br></p><p>sdfgsdfg sdfg sdfg sdfg sdfg sdfg&nbsp; &nbsp; &nbsp; &nbsp;asdf asdf&nbsp;</p><p>asdasdasd a asdasd&nbsp;</p>",
    "author": 2,
    "date": "2025-05-15T16:06:54.162Z"
  },
  {
    "fileName": "2.txt",
    "content": "<p><br></p><p>sdfgsdfg sdfg sdfg sdfg sdfg sdfg&nbsp; &nbsp; &nbsp; &nbsp;asdf asdf&nbsp;</p><p>asdasdasd a asdasd&nbsp;</p>",
    "author": 2,
    "date": "2025-05-15T16:07:16.670Z"
  },
  {
    "fileName": "2.txt",
    "content": "<p><br></p><p>sdfgsdfg sdfg sdfg sdfg sdfg sdfg&nbsp; &nbsp; &nbsp; &nbsp;asdf asdf&nbsp;</p><p>asdasdasd a asdasd&nbsp;</p>",
    "author": 2,
    "date": "2025-05-15T16:08:21.773Z"
  },
  {
    "fileName": "2.txt",
    "content": "<p><br></p><p>sdfgsdfg sdfg sdfg sdfg sdfg sdfg&nbsp; &nbsp; &nbsp; &nbsp;asdf asdf&nbsp;</p><p>asdasdasd a asdasd&nbsp;</p>",
    "author": 2,
    "date": "2025-05-15T16:09:35.573Z"
  },
  {
    "fileName": "2.txt",
    "content": "<p><br></p><p>sdfgsdfg sdfg sdfg sdfg sdfg sdfg&nbsp; &nbsp; &nbsp; &nbsp;asdf asdf&nbsp;</p><p>asdasdasd a asdasd&nbsp;</p>",
    "author": 2,
    "date": "2025-05-15T16:09:53.252Z"
  },
  {
    "fileName": "2.txt",
    "content": "<p><br></p><p>sdfgsdfg sdfg sdfg sdfg sdfg sdfg&nbsp; &nbsp; &nbsp; &nbsp;asdf asdf&nbsp;</p><p>asdasdasd a asdasd&nbsp;</p>",
    "author": 2,
    "date": "2025-05-15T16:10:41.276Z"
  },
  {
    "fileName": "2.txt",
    "content": "<p><br></p><p>sdfgsdfg sdfg sdfg sdfg sdfg sdfg&nbsp; &nbsp; &nbsp; &nbsp;asdf asdf&nbsp;</p><p>asdasdasd a asdasd&nbsp;</p>",
    "author": 2,
    "date": "2025-05-15T16:26:45.513Z"
  },
  {
    "fileName": "2.txt",
    "content": "<p><br></p><p>sdfgsdfg sdfg sdfg sdfg sdfg sdfg&nbsp; &nbsp; &nbsp; &nbsp;asdf asdf&nbsp;</p><p>asdasdasd a asdasd&nbsp;</p><p><br></p>",
    "author": 2,
    "date": "2025-05-15T16:26:48.485Z"
  },
  {
    "fileName": "2.txt",
    "content": "<p><br></p><p>sdfgsdfg sdfg sdfg sdfg sdfg sdfg&nbsp; &nbsp; &nbsp; &nbsp;asdf asdf&nbsp;</p><p>asdasdasd a asdasd&nbsp;</p><p>a</p>",
    "author": 2,
    "date": "2025-05-15T16:26:49.318Z"
  },
  {
    "fileName": "2.txt",
    "content": "<p><br></p><p>sdfgsdfg sdfg sdfg sdfg sdfg sdfg&nbsp; &nbsp; &nbsp; &nbsp;asdf asdf&nbsp;</p><p>asdasdasd a asdasd&nbsp;</p><p>asd</p>",
    "author": 2,
    "date": "2025-05-15T16:26:49.425Z"
  },
  {
    "fileName": "2.txt",
    "content": "<p><br></p><p>sdfgsdfg sdfg sdfg sdfg sdfg sdfg&nbsp; &nbsp; &nbsp; &nbsp;asdf asdf&nbsp;</p><p>asdasdasd a asdasd&nbsp;</p><p>asdf</p>",
    "author": 2,
    "date": "2025-05-15T16:26:49.635Z"
  },
  {
    "fileName": "2.txt",
    "content": "<p><br></p><p>sdfgsdfg sdfg sdfg sdfg sdfg sdfg&nbsp; &nbsp; &nbsp; &nbsp;asdf asdf&nbsp;</p><p>asdasdasd a asdasd&nbsp;</p><p>asdf</p><p><br></p>",
    "author": 2,
    "date": "2025-05-15T16:26:49.998Z"
  },
  {
    "fileName": "2.txt",
    "content": "<p><br></p><p>sdfgsdfg sdfg sdfg sdfg sdfg sdfg&nbsp; &nbsp; &nbsp; &nbsp;asdf asdf&nbsp;</p><p>asdasdasd a asdasd&nbsp;</p><p>asdf</p><p>asd</p>",
    "author": 2,
    "date": "2025-05-15T16:26:50.703Z"
  },
  {
    "fileName": "2.txt",
    "content": "<p><br></p><p>sdfgsdfg sdfg sdfg sdfg sdfg sdfg&nbsp; &nbsp; &nbsp; &nbsp;asdf asdf&nbsp;</p><p>asdasdasd a asdasd&nbsp;</p><p>asdf</p><p>asdf</p>",
    "author": 2,
    "date": "2025-05-15T16:26:50.906Z"
  },
  {
    "fileName": "2.txt",
    "content": "<p><br></p><p>sdfgsdfg sdfg sdfg sdfg sdfg sdfg&nbsp; &nbsp; &nbsp; &nbsp;asdf asdf&nbsp;</p><p>asdasdasd a asdasd&nbsp;</p><p>asdf</p><p>asdfsa</p>",
    "author": 2,
    "date": "2025-05-15T16:26:51.007Z"
  },
  {
    "fileName": "2.txt",
    "content": "<p><br></p><p>sdfgsdfg sdfg sdfg sdfg sdfg sdfg&nbsp; &nbsp; &nbsp; &nbsp;asdf asdf&nbsp;</p><p>asdasdasd a asdasd&nbsp;</p><p>asdf</p><p>asdfsad</p>",
    "author": 2,
    "date": "2025-05-15T16:26:51.108Z"
  },
  {
    "fileName": "2.txt",
    "content": "<p><br></p><p>sdfgsdfg sdfg sdfg sdfg sdfg sdfg&nbsp; &nbsp; &nbsp; &nbsp;asdf asdf&nbsp;</p><p>asdasdasd a asdasd&nbsp;</p><p>asdf</p><p>asdfsadf</p>",
    "author": 2,
    "date": "2025-05-15T16:26:51.215Z"
  },
  {
    "fileName": "2.txt",
    "content": "<p><br></p><p>sdfgsdfg sdfg sdfg sdfg sdfg sdfg&nbsp; &nbsp; &nbsp; &nbsp;asdf asdf&nbsp;</p><p>asdasdasd a asdasd&nbsp;</p><p>asdf</p><p>asdfsadf</p><p><br></p>",
    "author": 2,
    "date": "2025-05-15T16:26:51.316Z"
  },
  {
    "fileName": "2.txt",
    "content": "<p><br></p><p>sdfgsdfg sdfg sdfg sdfg sdfg sdfg&nbsp; &nbsp; &nbsp; &nbsp;asdf asdf&nbsp;</p><p>asdasdasd a asdasd&nbsp;</p><p>asdf</p><p>asdfsadf</p><p><br></p><p><br></p>",
    "author": 2,
    "date": "2025-05-15T16:26:51.568Z"
  },
  {
    "fileName": "2.txt",
    "content": "<p><br></p><p>sdfgsdfg sdfg sdfg sdfg sdfg sdfg&nbsp; &nbsp; &nbsp; &nbsp;asdf asdf&nbsp;</p><p>asdasdasd a asdasd&nbsp;</p><p>asdf</p><p>asdfsadf</p><p><br></p><p><br></p>",
    "author": 2,
    "date": "2025-05-15T16:26:52.750Z"
  },
  {
    "fileName": "2.txt",
    "content": "<p><br></p><p>sdfgsdfg sdfg sdfg sdfg sdfg sdfg&nbsp; &nbsp; &nbsp; &nbsp;asdf asdf&nbsp;</p><p>asdasdasd a asdasd a</p>",
    "author": 2,
    "date": "2025-05-15T16:26:53.225Z"
  },
  {
    "fileName": "2.txt",
    "content": "<p><br></p><p>sdfgsdfg sdfg sdfg sdfg sdfg sdfg&nbsp; &nbsp; &nbsp; &nbsp;asdf asdf&nbsp;</p><p>asdasdasd a asdasd&nbsp;</p><p>asdf</p><p>asdfsadf</p><p><br></p><p><br></p>",
    "author": 2,
    "date": "2025-05-15T16:26:57.271Z"
  },
  {
    "fileName": "2.txt",
    "content": "<p><br></p><p>sdfgsdfg sdfg sdfg sdfg sdfg sdfg&nbsp; &nbsp; &nbsp; &nbsp;asdf asdf&nbsp;</p><p>asdasdasd a asdasd&nbsp;</p><p>asdf</p><p>asdfsadf</p><p><br></p><p><br></p>",
    "author": 2,
    "date": "2025-05-15T16:28:35.493Z"
  },
  {
    "fileName": "2.txt",
    "content": "<p><br></p><p>sdfgsdfg sdfg sdfg sdfg sdfg sdfg&nbsp; &nbsp; &nbsp; &nbsp;asdf asdf&nbsp;</p><p>asdasdasd a asdasd&nbsp;</p><p>asdf&nbsp;</p><p>asdfsadf</p><p><br></p><p><br></p>",
    "author": 2,
    "date": "2025-05-15T16:28:37.569Z"
  },
  {
    "fileName": "2.txt",
    "content": "<p><br></p><p>sdfgsdfg sdfg sdfg sdfg sdfg sdfg&nbsp; &nbsp; &nbsp; &nbsp;asdf asdf&nbsp;</p><p>asdasdasd a asdasd&nbsp;</p><p>asdf aasdfsadf</p><p><br></p><p><br></p>",
    "author": 2,
    "date": "2025-05-15T16:28:37.772Z"
  },
  {
    "fileName": "2.txt",
    "content": "<p><br></p><p>sdfgsdfg sdfg sdfg sdfg sdfg sdfg&nbsp; &nbsp; &nbsp; &nbsp;asdf asdf&nbsp;</p><p>asdasdasd a asdasd&nbsp;</p><p>asdf aaasdfsadf</p><p><br></p><p><br></p>",
    "author": 2,
    "date": "2025-05-15T16:28:38.014Z"
  },
  {
    "fileName": "2.txt",
    "content": "<p><br></p><p>sdfgsdfg sdfg sdfg sdfg sdfg sdfg&nbsp; &nbsp; &nbsp; &nbsp;asdf asdf&nbsp;</p><p>asdasdasd a asdasd&nbsp;</p><p>asdf aasasdfsadf</p><p><br></p><p><br></p>",
    "author": 2,
    "date": "2025-05-15T16:28:38.115Z"
  },
  {
    "fileName": "2.txt",
    "content": "<p><br></p><p>sdfgsdfg sdfg sdfg sdfg sdfg sdfg&nbsp; &nbsp; &nbsp; &nbsp;asdf asdf&nbsp;</p><p>asdasdasd a asdasd&nbsp;</p><p>asdf aasdasdfsadf</p><p><br></p><p><br></p>",
    "author": 2,
    "date": "2025-05-15T16:28:38.217Z"
  },
  {
    "fileName": "2.txt",
    "content": "<p><br></p><p>sdfgsdfg sdfg sdfg sdfg sdfg sdfg&nbsp; &nbsp; &nbsp; &nbsp;asdf asdf&nbsp;</p><p>asdasdasd a asdasd&nbsp;</p><p>asdf aasd asdfsadf</p><p><br></p><p><br></p>",
    "author": 2,
    "date": "2025-05-15T16:28:38.317Z"
  },
  {
    "fileName": "2.txt",
    "content": "<p><br></p><p>sdfgsdfg sdfg sdfg sdfg sdfg sdfg&nbsp; &nbsp; &nbsp; &nbsp;asdf asdf&nbsp;</p><p>asdasdasd a asdasd&nbsp;</p><p>asdf aasd aasdfsadf</p><p><br></p><p><br></p>",
    "author": 2,
    "date": "2025-05-15T16:28:38.418Z"
  },
  {
    "fileName": "2.txt",
    "content": "<p><br></p><p>sdfgsdfg sdfg sdfg sdfg sdfg sdfg&nbsp; &nbsp; &nbsp; &nbsp;asdf asdf&nbsp;</p><p>asdasdasd a asdasd&nbsp;</p><p>asdf aasd asasdfsadf</p><p><br></p><p><br></p>",
    "author": 2,
    "date": "2025-05-15T16:28:38.519Z"
  },
  {
    "fileName": "2.txt",
    "content": "<p><br></p><p>sdfgsdfg sdfg sdfg sdfg sdfg sdfg&nbsp; &nbsp; &nbsp; &nbsp;asdf asdf&nbsp;</p><p>asdasdasd a asdasd&nbsp;</p><p>asdf aasd asasdfsadf</p><p><br></p><p><br></p>",
    "author": 2,
    "date": "2025-05-15T16:28:38.770Z"
  },
  {
    "fileName": "2.txt",
    "content": "<p><br></p><p>sdfgsdfg sdfg sdfg sdfg sdfg sdfg&nbsp; &nbsp; &nbsp; &nbsp;asdf asdf&nbsp;</p><p>asdasdasd a asdasd&nbsp;</p><p>asdf</p><p>asdfsadf</p><p>a</p><p><br></p>",
    "author": 2,
    "date": "2025-05-15T16:28:39.312Z"
  },
  {
    "fileName": "2.txt",
    "content": "<p><br></p><p>sdfgsdfg sdfg sdfg sdfg sdfg sdfg&nbsp; &nbsp; &nbsp; &nbsp;asdf asdf&nbsp;</p><p>asdasdasd a asdasd&nbsp;</p><p>asdf aasd asasdfsadf</p><p>a</p><p><br></p>",
    "author": 2,
    "date": "2025-05-15T16:32:56.751Z"
  },
  {
    "fileName": "2.txt",
    "content": "<p><br></p><p>sdfgsdfg sdfg sdfg sdfg sdfg sdfg&nbsp; &nbsp; &nbsp; &nbsp;asdf asdf&nbsp;</p><p>asdasdasd a asdasd&nbsp;</p><p>asdf aasd asasdfsadf</p><p><br></p><p>a</p><p><br></p>",
    "author": 2,
    "date": "2025-05-15T16:33:09.270Z"
  },
  {
    "fileName": "2.txt",
    "content": "<p><br></p><p>sdfgsdfg sdfg sdfg sdfg sdfg sdfg&nbsp; &nbsp; &nbsp; &nbsp;asdf asdf&nbsp;</p><p>asdasdasd a asdasd&nbsp;</p><p>asdf aasd asasdfsadf</p><p>as</p><p>a</p><p><br></p>",
    "author": 2,
    "date": "2025-05-15T16:33:10.264Z"
  },
  {
    "fileName": "2.txt",
    "content": "<p><br></p><p>sdfgsdfg sdfg sdfg sdfg sdfg sdfg&nbsp; &nbsp; &nbsp; &nbsp;asdf asdf&nbsp;</p><p>asdasdasd a asdasd&nbsp;</p><p>asdf aasd asasdfsadf</p><p>asd</p><p>a</p><p><br></p>",
    "author": 2,
    "date": "2025-05-15T16:33:10.370Z"
  },
  {
    "fileName": "2.txt",
    "content": "<p><br></p><p>sdfgsdfg sdfg sdfg sdfg sdfg sdfg&nbsp; &nbsp; &nbsp; &nbsp;asdf asdf&nbsp;</p><p>asdasdasd a asdasd&nbsp;</p><p>asdf aasd asasdfsadf</p><p>asdas</p><p>a</p><p><br></p>",
    "author": 2,
    "date": "2025-05-15T16:33:10.696Z"
  },
  {
    "fileName": "2.txt",
    "content": "<p><br></p><p>sdfgsdfg sdfg sdfg sdfg sdfg sdfg&nbsp; &nbsp; &nbsp; &nbsp;asdf asdf&nbsp;</p><p>asdasdasd a asdasd&nbsp;</p><p>asdf aasd asasdfsadf</p><p>asdasd</p><p>a</p><p><br></p>",
    "author": 2,
    "date": "2025-05-15T16:33:10.927Z"
  },
  {
    "fileName": "2.txt",
    "content": "<p><br></p><p>sdfgsdfg sdfg sdfg sdfg sdfg sdfg&nbsp; &nbsp; &nbsp; &nbsp;asdf asdf&nbsp;</p><p>asdasdasd a asdasd&nbsp;</p><p>asdf aasd asasdfsadf</p><p>asdasd</p><p>a</p><p><br></p>",
    "author": 2,
    "date": "2025-05-15T16:33:23.344Z"
  }
]